myne_tabular_classification_package/__init__.py
myne_tabular_classification_package/k_neighbors_classifier.py
myne_tabular_classification_package/logistic_regression.py
myne_tabular_classification_package/random_forest_classifier.py
myne_tabular_classification_package/svc.py
myne_tabular_classification_package/tabular_classification_model.py
myne_tabular_classification_package/tabular_classification_task.py
myne_tabular_classification_package-1.0.0.dist-info/METADATA
myne_tabular_classification_package-1.0.0.dist-info/WHEEL
myne_tabular_classification_package-1.0.0.dist-info/entry_points.txt
myne_tabular_classification_package-1.0.0.dist-info/RECORD
