Metadata-Version: 2.3
Name: myne_tabular_classification_package
Version: 1.0.0
Summary: Tabular Classification Package
Project-URL: Homepage, https://github.com/DashAISoftware/DashAI
Project-URL: Issues, https://github.com/DashAISoftware/DashAI/issues
Author-email: DashAI team <dashaisoftware@gmail.com>
Requires-Python: >=3.8
Requires-Dist: scikit-learn>=1.2.1
